waiter/__main__.py
waiter/action.py
waiter/cli.py
waiter/configuration.py
waiter/data_format.py
waiter/display.py
waiter/format.py
waiter/http_util.py
waiter/instance_select.py
waiter/metrics.py
waiter/plugins.py
waiter/querying.py
waiter/terminal.py
waiter/token_post.py
waiter/util.py
waiter/version.py
waiter/subcommands/__init__.py
waiter/subcommands/create.py
waiter/subcommands/delete.py
waiter/subcommands/init.py
waiter/subcommands/instance.py
waiter/subcommands/kill.py
waiter/subcommands/maintenance.py
waiter/subcommands/ping.py
waiter/subcommands/ready.py
waiter/subcommands/show.py
waiter/subcommands/ssh.py
waiter/subcommands/ssl.py
waiter/subcommands/tokens.py
waiter/subcommands/update.py
waiter_client-1.5.7.dist-info/METADATA
waiter_client-1.5.7.dist-info/WHEEL
waiter_client-1.5.7.dist-info/entry_points.txt
waiter_client-1.5.7.dist-info/top_level.txt
waiter_client-1.5.7.dist-info/RECORD
