Metadata-Version: 2.1
Name: waiter-client
Version: 1.5.7
Summary: Two Sigma's Waiter CLI
Requires-Dist: arrow (>=0.13.1)
Requires-Dist: humanfriendly (>=4.18)
Requires-Dist: pyyaml (>=3.13)
Requires-Dist: requests (>=2.20.0)
Requires-Dist: retrying (>=1.3.3)
Requires-Dist: tabulate (>=0.8.3)
Provides-Extra: test
Requires-Dist: pytest ; extra == 'test'
